ekushey/__init__.py
ekushey/feature_extraction.py
ekushey/kalpurush.ttf
ekushey-0.6.dist-info/LICENSE
ekushey-0.6.dist-info/METADATA
ekushey-0.6.dist-info/WHEEL
ekushey-0.6.dist-info/top_level.txt
ekushey-0.6.dist-info/RECORD
