Metadata-Version: 2.1
Name: ekushey
Version: 0.6
Summary: UNKNOWN
Home-page: https://github.com/Kowsher/Bangla-NLP/tree/master/Bangla%20Feature%20Extraction
Author: Karigor
Author-email: 
License: MIT
Platform: UNKNOWN
Classifier: Programming Language :: Python :: 3
Classifier: License :: OSI Approved :: MIT License
Classifier: Operating System :: OS Independent
Requires-Dist: scipy
Requires-Dist: gensim
Requires-Dist: numpy
Requires-Dist: matplotlib
Requires-Dist: scikit-learn
Requires-Dist: glove-python
